setup.py
mj_azure_iot_pnp_device/__init__.py
mj_azure_iot_pnp_device.egg-info/PKG-INFO
mj_azure_iot_pnp_device.egg-info/SOURCES.txt
mj_azure_iot_pnp_device.egg-info/dependency_links.txt
mj_azure_iot_pnp_device.egg-info/requires.txt
mj_azure_iot_pnp_device.egg-info/top_level.txt
mj_azure_iot_pnp_device/contents/__init__.py
mj_azure_iot_pnp_device/contents/contents.py
mj_azure_iot_pnp_device/device/__init__.py
mj_azure_iot_pnp_device/device/iothub_device_client.py